{
  "project_info": {
    "project_number": "1090944814723",
    "firebase_url": "https://dbconnectivity-28daa-default-rtdb.firebaseio.com",
    "project_id": "dbconnectivity-28daa",
    "storage_bucket": "dbconnectivity-28daa.appspot.com"
  },
  "client": [
    {
      "client_info": {
        "mobilesdk_app_id": "1:1090944814723:android:9655713c798fb14ca495b6",
        "android_client_info": {
          "package_name": "com.example.dbconnectivity"
        }
      },
      "oauth_client": [
        {
          "client_id": "1090944814723-d7b30dfca5l7qr2bu8f15pj19b64ksul.apps.googleusercontent.com",
          "client_type": 3
        }
      ],
      "api_key": [
        {
          "current_key": "AIzaSyBClLGNLAtitOhczL19S8JQUEnV-Z1pLwI"
        }
      ],
      "services": {
        "appinvite_service": {
          "other_platform_oauth_client": [
            {
              "client_id": "1090944814723-d7b30dfca5l7qr2bu8f15pj19b64ksul.apps.googleusercontent.com",
              "client_type": 3
            }
          ]
        }
      }
    }
  ],
  "configuration_version": "1"
}